CS158-S1-2.v
module CS158_S1_2(
    a,b,c,d,w,x,y,z,p,q,r,s
);
    input a,b,c,d ;
    output w,x,y,z;
    output p,q,r,s;
    wire na,nb,nc,nd;
    wire w1, w2, w3, w4, w5, w6, w7, w8, w9, w10, w11, w12;
    wire f,g;

/*
    not (na, a);
    not (nb, b);
    not (nc, c);
    not (nd, d);

    // q
    and (w1, a, nb);
    and (w2, na, b, c);
    or (w3, w1, w2);

    // r
    and (w4,na,b);
    and (w5, b, nc);
    and (w6, a, nb, nc);
    or (w7, w4, w5, w6);

    // s
*/
    // Data Flow
    assign w = a&b&d;
    assign x = (a&~b&d) | (a&~b&c) | (~a&b&c&~d);
    assign y = (~a&b&~c) | (a&~b&c);
    assign z = (~a&b&~c&~d) | (~a&~b&c&~d) | (a&b&c&d) | (a&~b&~c&d) | (a&~b&c&~d);

    assign p = a&b&d;
    assign q = (a&~b&d) | (a&~b&c) | (~a&b&c&~d);
    assign r = (~a&b&~c) | (a&~b&c);
    assign s = (~a&b&~c&~d) | (~a&~b&c&~d) | (a&b&c&d) | (a&~b&~c&d) | (a&~b&c&~d);
endmodule



















    /*
    assign w = a;
    assign x = (a&~b) | (~a & b & c);
    assign y = (~a&b) | (b&~c) | (a&~b&~c);
    assign z = ~d;
    */

231CS158 - Lab 5 - 27.08.2024/CS158-S1-2_tb.v
module CS158_S1_2_tb;
    reg a,b,c,d;
    wire p,q,r,s,w,x,y,z;
    CS158_S1_2 test(a,b,c,d,w,x,y,z,p,q,r,s);

    initial begin
        {a,b,c,d} = 0;
        for(integer i = 1; i < 10; i++)
            begin
                #10 {a,b,c,d} = i;
            end;
        $finish;
    end


    initial begin
        $dumpfile("CS158_S1_2.vcd");
        $dumpvars(0,CS158_S1_2_tb);
        $display("---------------------------CS158 S1-2---------------------------");
        $display("-----------------6 3 1 -1 to 8 4 2 1 converter -----------------");
        $display("| Time | 6 3 1 -1 | dataflow 6 3 2 11 | gateflow 8 4 2 1");
        $monitor("| %4d | %1b %1b %1b %1b | %10b %1b %1b %1b | %10b %1b %1b %1b |", $time,a,b,c,d,w,x,y,z,p,q,r,s);
        $display("----------------------------------------------------------------");
    end
endmodule

CS158_S1_2.vcd
$date
	Tue Aug 27 17:00:43 2024
$end
$version
	Icarus Verilog
$end
$timescale
	1s
$end
$scope module CS158_S1_2_tb $end
$var wire 1 ! z $end
$var wire 1 " y $end
$var wire 1 # x $end
$var wire 1 $ w $end
$var wire 1 % s $end
$var wire 1 & r $end
$var wire 1 ' q $end
$var wire 1 ( p $end
$var reg 1 ) a $end
$var reg 1 * b $end
$var reg 1 + c $end
$var reg 1 , d $end
$scope module test $end
$var wire 1 ) a $end
$var wire 1 * b $end
$var wire 1 + c $end
$var wire 1 , d $end
$var wire 1 ( p $end
$var wire 1 ' q $end
$var wire 1 & r $end
$var wire 1 % s $end
$var wire 1 $ w $end
$var wire 1 # x $end
$var wire 1 " y $end
$var wire 1 ! z $end
$upscope $end
$scope begin $ivl_for_loop0 $end
$var integer 32 - i [31:0] $end
$upscope $end
$upscope $end
$enddefinitions $end
#0
$dumpvars
b1 -
0,
0+
0*
0)
0(
0'
0&
0%
0$
0#
0"
0!
$end
#10
b10 -
1,
#20
1!
1%
b11 -
1+
0,
#30
0!
0%
b100 -
1,
#40
1!
1%
1"
1&
b101 -
1*
0+
0,
#50
0!
0%
b110 -
1,
#60
0!
0%
0"
0&
1#
1'
b111 -
1+
0,
#70
0#
0'
b1000 -
1,
#80
b1001 -
1)
0*
0+
0,
#90
1#
1!
1'
1%
b1010 -
1,
